wowool/portal/__init__.py
wowool/portal/client/argument_parser.py
wowool/portal/client/cli.py
wowool/portal/client/components.py
wowool/portal/client/defines.py
wowool/portal/client/environment.py
wowool/portal/client/error.py
wowool/portal/client/pipeline.py
wowool/portal/client/portal.py
wowool/portal/client/service.py
wowool/portal/client/version.py
wowool/portal/wow/__main__.py
wowool/portal/wow/argument_parser.py
wowool/portal/wow/command/__init__.py
wowool/portal/wow/command/components.py
wowool/portal/wow/command/process.py
wowool/portal/wow/command/version.py
wowool_portal-1.4.0.dist-info/METADATA
wowool_portal-1.4.0.dist-info/WHEEL
wowool_portal-1.4.0.dist-info/entry_points.txt
wowool_portal-1.4.0.dist-info/top_level.txt
wowool_portal-1.4.0.dist-info/RECORD
