Metadata-Version: 2.1
Name: wowool-portal
Version: 1.4.0
Summary: Wowool Portal Client
Home-page: https://www.wowool.com/
Author: Wowool
Author-email: info@wowool.com
Requires-Python: >=3.9
Requires-Dist: wowool-common<3.7.0,>=3.6.0
Requires-Dist: requests
Requires-Dist: jsonpath-ng
Requires-Dist: unidecode
Requires-Dist: rich
